COPYING
MANIFEST.in
README.rst
bootstrap.py
buildout.cfg
setup.py
config/features/htk.py
config/features/lfcc_60.py
config/features/mfcc_60.py
config/features/mfcc_90.py
config/features/spro.py
config/grid/demanding.py
config/grid/grid.py
config/grid/local.py
config/grid/para_training_local.py
config/grid/para_training_sge.py
config/grid/very_demanding.py
config/preprocessing/energy.py
config/preprocessing/energy_mic.py
config/preprocessing/energy_thr.py
config/preprocessing/external.py
config/preprocessing/mod_4hz.py
config/tools/isv/isv_256g_u50.py
config/tools/isv/isv_512g_u100.py
config/tools/isv/isv_512g_u200.py
config/tools/isv/isv_512g_u50.py
config/tools/isv/isv_8g_u20.py
config/tools/ivec/ivec_1024G_600T.py
config/tools/ivec/ivec_2048_cosine.py
config/tools/ivec/ivec_256G_400T.py
config/tools/ivec/ivec_512G_400T.py
config/tools/ivec/plda_simp.py
config/tools/ivec/plda_std.py
config/tools/ivec/plda_two-cov.py
config/tools/ivec/plda_lda/plda_simp_lda100.py
config/tools/ivec/plda_lda/plda_simp_lda200.py
config/tools/ivec/plda_lda/plda_simp_lda300.py
config/tools/ivec/plda_lda/plda_simp_lda400.py
config/tools/ivec/plda_lda/plda_simp_lda500.py
config/tools/ivec/plda_lda/plda_simp_lda600.py
config/tools/ivec/plda_lda/plda_two-cov_lda100.py
config/tools/ivec/plda_lda/plda_two-cov_lda200.py
config/tools/ivec/plda_lda/plda_two-cov_lda300.py
config/tools/ivec/plda_lda/plda_two-cov_lda400.py
config/tools/ivec/plda_lda/plda_two-cov_lda500.py
config/tools/ivec/plda_lda/plda_two-cov_lda600.py
config/tools/jfa/jfa_256_v10_u10.py
config/tools/jfa/jfa_256_v5_u10.py
config/tools/jfa/jfa_8_v_5_u_5.py
config/tools/ubm_gmm/ubm_gmm_256G.py
config/tools/ubm_gmm/ubm_gmm_512G.py
config/tools/ubm_gmm/ubm_gmm_512G_regular_scoring.py
config/tools/ubm_gmm/ubm_gmm_8G.py
xspear/__init__.py
xspear.fast_plda.egg-info/PKG-INFO
xspear.fast_plda.egg-info/SOURCES.txt
xspear.fast_plda.egg-info/dependency_links.txt
xspear.fast_plda.egg-info/entry_points.txt
xspear.fast_plda.egg-info/namespace_packages.txt
xspear.fast_plda.egg-info/requires.txt
xspear.fast_plda.egg-info/top_level.txt
xspear/fast_plda/__init__.py
xspear/fast_plda/script/__init__.py
xspear/fast_plda/script/evaluate_new.py
xspear/fast_plda/script/ivec_whitening_lnorm.py
