Metadata-Version: 1.1
Name: xspear.fast-plda
Version: 1.1.1
Summary: Toolchains for speaker recognition and anti-spoofing using PLDA
Home-page: http://pypi.python.org/pypi/spear.fast_plda
Author: Aleksandr Sizov, Elie Khoury
Author-email: sizov@cs.uef.fi, Elie.Khoury@idiap.ch
License: GPLv3
Keywords: bob,xbob,xbob.db,speaker recognition,plda
Platform: UNKNOWN
Classifier: Development Status :: 4 - Beta
Classifier: Intended Audience :: Developers
Classifier: License :: OSI Approved :: GNU General Public License v3 (GPLv3)
Classifier: Natural Language :: English
Classifier: Programming Language :: Python
Classifier: Programming Language :: Python :: 3
Classifier: Topic :: Scientific/Engineering :: Artificial Intelligence
